geo_sight/cli.py
geo_sight/utils.py
locatorpoint-1.0.0.dist-info/DESCRIPTION.rst
locatorpoint-1.0.0.dist-info/METADATA
locatorpoint-1.0.0.dist-info/RECORD
locatorpoint-1.0.0.dist-info/WHEEL
locatorpoint-1.0.0.dist-info/entry_points.txt
locatorpoint-1.0.0.dist-info/metadata.json
locatorpoint-1.0.0.dist-info/top_level.txt
