Metadata-Version: 2.0
Name: locatorpoint
Version: 1.0.0
Summary: Python Package to get the information from Geo Coordinates
Home-page: https://github.com/mandiladitya
Author: Aditya Mandil
Author-email: adityamandil317@gmail.com
License: MIT
Platform: UNKNOWN
Classifier: License :: OSI Approved :: MIT License
Classifier: Programming Language :: Python :: 3
Classifier: Programming Language :: Python :: 3.7
Requires-Dist: geopy
Requires-Dist: requests
Requires-Dist: wolframalpha
